audioeqinfer/__init__.py
audioeqinfer/densityrepr.py
audioeqinfer/finder.py
audioeqinfer/parameterfunction.py
audioeqinfer/utils.py
audioeqinfer-0.1.0.dist-info/licenses/LICENSE
audioeqinfer-0.1.0.dist-info/METADATA
audioeqinfer-0.1.0.dist-info/WHEEL
audioeqinfer-0.1.0.dist-info/top_level.txt
audioeqinfer-0.1.0.dist-info/RECORD
