Metadata-Version: 2.4
Name: audioeqinfer
Version: 0.1.0
Summary: Probabilistic Equalization Discovery for Audio Signals
Author-email: Liam Deaton <williambradydeaton@gmail.com>
License-Expression: MIT
Keywords: Audio Equalizer,Equalizer Inference
Classifier: Programming Language :: Python :: 3
Requires-Python: >=3.8
License-File: LICENSE
Requires-Dist: requests
Requires-Dist: importlib-metadata; python_version < "3.10"
Requires-Dist: numpy
Requires-Dist: scipy
Requires-Dist: torch
Requires-Dist: nflows
Requires-Dist: patsy
Requires-Dist: pedalboard
Requires-Dist: statsmodels
Requires-Dist: matplotlib
Dynamic: license-file
